zyte_api/__init__.py
zyte_api/__main__.py
zyte_api/__version__.py
zyte_api/_async.py
zyte_api/_errors.py
zyte_api/_retry.py
zyte_api/_sync.py
zyte_api/_utils.py
zyte_api/_x402.py
zyte_api/apikey.py
zyte_api/constants.py
zyte_api/errors.py
zyte_api/stats.py
zyte_api/utils.py
zyte_api/aio/__init__.py
zyte_api/aio/client.py
zyte_api/aio/errors.py
zyte_api/aio/retry.py
zyte_api-0.8.0.dist-info/licenses/LICENSE
zyte_api-0.8.0.dist-info/METADATA
zyte_api-0.8.0.dist-info/WHEEL
zyte_api-0.8.0.dist-info/entry_points.txt
zyte_api-0.8.0.dist-info/top_level.txt
zyte_api-0.8.0.dist-info/RECORD
