Metadata-Version: 2.4
Name: zyte-api
Version: 0.8.0
Summary: Python interface to Zyte API
Home-page: https://github.com/zytedata/python-zyte-api
Author: Zyte Group Ltd
Author-email: opensource@zyte.com
Classifier: Development Status :: 3 - Alpha
Classifier: Intended Audience :: Developers
Classifier: License :: OSI Approved :: BSD License
Classifier: Natural Language :: English
Classifier: Operating System :: OS Independent
Classifier: Programming Language :: Python :: 3
Classifier: Programming Language :: Python :: 3.9
Classifier: Programming Language :: Python :: 3.10
Classifier: Programming Language :: Python :: 3.11
Classifier: Programming Language :: Python :: 3.12
Classifier: Programming Language :: Python :: 3.13
License-File: LICENSE
Requires-Dist: aiohttp>=3.8.0
Requires-Dist: attrs>=20.1.0
Requires-Dist: brotli>=0.5.2
Requires-Dist: runstats>=0.0.1
Requires-Dist: tenacity>=8.2.0
Requires-Dist: tqdm>=4.16.0
Requires-Dist: w3lib>=2.1.1
Provides-Extra: x402
Requires-Dist: eth-account>=0.13.7; extra == "x402"
Requires-Dist: x402>=0.1.1; extra == "x402"
Dynamic: author
Dynamic: author-email
Dynamic: classifier
Dynamic: description
Dynamic: description-content-type
Dynamic: home-page
Dynamic: license-file
Dynamic: provides-extra
Dynamic: requires-dist
Dynamic: summary
